v_m_t/AOLogger.py
v_m_t/S3WorkFileManager.py
v_m_t/VolumeInfoBase.py
v_m_t/VolumeInfoBuda.py
v_m_t/VolumeInfoeXist.py
v_m_t/__init__.py
v_m_t/detectgraynb.py
v_m_t/getS3FolderPrefix.py
v_m_t/init_app_logger.py
v_m_t/manifestforwork.py
v_m_t/s3customtransfer.py
v_m_t/test_expandImageList.py
volume_manifest_tool-1.0.2.dist-info/LICENSE
volume_manifest_tool-1.0.2.dist-info/METADATA
volume_manifest_tool-1.0.2.dist-info/WHEEL
volume_manifest_tool-1.0.2.dist-info/entry_points.txt
volume_manifest_tool-1.0.2.dist-info/top_level.txt
volume_manifest_tool-1.0.2.dist-info/RECORD
