Metadata-Version: 2.1
Name: volume-manifest-tool
Version: 1.0.2
Summary: Creates manifests for syncd works.
Home-page: https://github.com/buda-base/volume-manifest-tool/
Author: jimk
Author-email: jimk@tbrc.org
License: UNKNOWN
Platform: UNKNOWN
Classifier: Programming Language :: Python :: 3
Classifier: License :: OSI Approved :: MIT License
Classifier: Operating System :: MacOS :: MacOS X
Classifier: Operating System :: OS Independent
Classifier: Development Status :: 5 - Production/Stable
Requires-Python: >=3.6
Requires-Dist: boto3
Requires-Dist: requests
Requires-Dist: lxml
Requires-Dist: pillow
Requires-Dist: s3transfer
Requires-Dist: botocore
